{
  "id": 307858020,
  "node_id": "MDEwOlJlcG9zaXRvcnkzMDc4NTgwMjA=",
  "name": "one",
  "full_name": "catmullet/one",
  "private": false,
  "owner": {
    "login": "catmullet",
    "id": 35046964,
    "node_id": "MDQ6VXNlcjM1MDQ2OTY0",
    "avatar_url": "https://avatars.githubusercontent.com/u/35046964?v=4",
    "gravatar_id": "",
    "url": "https://api.github.com/users/catmullet",
    "html_url": "https://github.com/catmullet",
    "followers_url": "https://api.github.com/users/catmullet/followers",
    "following_url": "https://api.github.com/users/catmullet/following{/other_user}",
    "gists_url": "https://api.github.com/users/catmullet/gists{/gist_id}",
    "starred_url": "https://api.github.com/users/catmullet/starred{/owner}{/repo}",
    "subscriptions_url": "https://api.github.com/users/catmullet/subscriptions",
    "organizations_url": "https://api.github.com/users/catmullet/orgs",
    "repos_url": "https://api.github.com/users/catmullet/repos",
    "events_url": "https://api.github.com/users/catmullet/events{/privacy}",
    "received_events_url": "https://api.github.com/users/catmullet/received_events",
    "type": "User",
    "user_view_type": "public",
    "site_admin": false
  },
  "html_url": "https://github.com/catmullet/one",
  "description": "\ud83d\udea5 Idempotency Handler, for making sure incoming requests are idempotent. Useful for payments, \"at least once delivery\" systems and more.",
  "fork": false,
  "url": "https://api.github.com/repos/catmullet/one",
  "forks_url": "https://api.github.com/repos/catmullet/one/forks",
  "keys_url": "https://api.github.com/repos/catmullet/one/keys{/key_id}",
  "collaborators_url": "https://api.github.com/repos/catmullet/one/collaborators{/collaborator}",
  "teams_url": "https://api.github.com/repos/catmullet/one/teams",
  "hooks_url": "https://api.github.com/repos/catmullet/one/hooks",
  "issue_events_url": "https://api.github.com/repos/catmullet/one/issues/events{/number}",
  "events_url": "https://api.github.com/repos/catmullet/one/events",
  "assignees_url": "https://api.github.com/repos/catmullet/one/assignees{/user}",
  "branches_url": "https://api.github.com/repos/catmullet/one/branches{/branch}",
  "tags_url": "https://api.github.com/repos/catmullet/one/tags",
  "blobs_url": "https://api.github.com/repos/catmullet/one/git/blobs{/sha}",
  "git_tags_url": "https://api.github.com/repos/catmullet/one/git/tags{/sha}",
  "git_refs_url": "https://api.github.com/repos/catmullet/one/git/refs{/sha}",
  "trees_url": "https://api.github.com/repos/catmullet/one/git/trees{/sha}",
  "statuses_url": "https://api.github.com/repos/catmullet/one/statuses/{sha}",
  "languages_url": "https://api.github.com/repos/catmullet/one/languages",
  "stargazers_url": "https://api.github.com/repos/catmullet/one/stargazers",
  "contributors_url": "https://api.github.com/repos/catmullet/one/contributors",
  "subscribers_url": "https://api.github.com/repos/catmullet/one/subscribers",
  "subscription_url": "https://api.github.com/repos/catmullet/one/subscription",
  "commits_url": "https://api.github.com/repos/catmullet/one/commits{/sha}",
  "git_commits_url": "https://api.github.com/repos/catmullet/one/git/commits{/sha}",
  "comments_url": "https://api.github.com/repos/catmullet/one/comments{/number}",
  "issue_comment_url": "https://api.github.com/repos/catmullet/one/issues/comments{/number}",
  "contents_url": "https://api.github.com/repos/catmullet/one/contents/{+path}",
  "compare_url": "https://api.github.com/repos/catmullet/one/compare/{base}...{head}",
  "merges_url": "https://api.github.com/repos/catmullet/one/merges",
  "archive_url": "https://api.github.com/repos/catmullet/one/{archive_format}{/ref}",
  "downloads_url": "https://api.github.com/repos/catmullet/one/downloads",
  "issues_url": "https://api.github.com/repos/catmullet/one/issues{/number}",
  "pulls_url": "https://api.github.com/repos/catmullet/one/pulls{/number}",
  "milestones_url": "https://api.github.com/repos/catmullet/one/milestones{/number}",
  "notifications_url": "https://api.github.com/repos/catmullet/one/notifications{?since,all,participating}",
  "labels_url": "https://api.github.com/repos/catmullet/one/labels{/name}",
  "releases_url": "https://api.github.com/repos/catmullet/one/releases{/id}",
  "deployments_url": "https://api.github.com/repos/catmullet/one/deployments",
  "created_at": "2020-10-27T23:57:16Z",
  "updated_at": "2025-07-20T19:19:02Z",
  "pushed_at": "2020-11-13T03:24:07Z",
  "git_url": "git://github.com/catmullet/one.git",
  "ssh_url": "git@github.com:catmullet/one.git",
  "clone_url": "https://github.com/catmullet/one.git",
  "svn_url": "https://github.com/catmullet/one",
  "homepage": "",
  "size": 38,
  "stargazers_count": 23,
  "watchers_count": 23,
  "language": "Go",
  "has_issues": true,
  "has_projects": true,
  "has_downloads": true,
  "has_wiki": true,
  "has_pages": false,
  "has_discussions": false,
  "forks_count": 2,
  "mirror_url": null,
  "archived": false,
  "disabled": false,
  "open_issues_count": 0,
  "license": {
    "key": "mit",
    "name": "MIT License",
    "spdx_id": "MIT",
    "url": "https://api.github.com/licenses/mit",
    "node_id": "MDc6TGljZW5zZTEz"
  },
  "allow_forking": true,
  "is_template": false,
  "web_commit_signoff_required": false,
  "topics": [
    "delivery",
    "golang",
    "idempotence",
    "idempotency",
    "idempotency-handler",
    "idempotency-key",
    "idempotent",
    "idempotent-requests",
    "payment",
    "redis",
    "storage"
  ],
  "visibility": "public",
  "forks": 2,
  "open_issues": 0,
  "watchers": 23,
  "default_branch": "master",
  "permissions": {
    "admin": false,
    "maintain": false,
    "push": false,
    "triage": false,
    "pull": true
  },
  "temp_clone_token": "",
  "network_count": 2,
  "subscribers_count": 3
}