{
  "id": 1068691618,
  "node_id": "R_kgDOP7Lwog",
  "name": "zori",
  "full_name": "ZoriHQ/zori",
  "private": false,
  "owner": {
    "login": "ZoriHQ",
    "id": 235764145,
    "node_id": "O_kgDODg15sQ",
    "avatar_url": "https://avatars.githubusercontent.com/u/235764145?v=4",
    "gravatar_id": "",
    "url": "https://api.github.com/users/ZoriHQ",
    "html_url": "https://github.com/ZoriHQ",
    "followers_url": "https://api.github.com/users/ZoriHQ/followers",
    "following_url": "https://api.github.com/users/ZoriHQ/following{/other_user}",
    "gists_url": "https://api.github.com/users/ZoriHQ/gists{/gist_id}",
    "starred_url": "https://api.github.com/users/ZoriHQ/starred{/owner}{/repo}",
    "subscriptions_url": "https://api.github.com/users/ZoriHQ/subscriptions",
    "organizations_url": "https://api.github.com/users/ZoriHQ/orgs",
    "repos_url": "https://api.github.com/users/ZoriHQ/repos",
    "events_url": "https://api.github.com/users/ZoriHQ/events{/privacy}",
    "received_events_url": "https://api.github.com/users/ZoriHQ/received_events",
    "type": "Organization",
    "user_view_type": "public",
    "site_admin": false
  },
  "html_url": "https://github.com/ZoriHQ/zori",
  "description": "revenue \u2192 attribution \u2192 clarity. Open Source Web Analytics",
  "fork": false,
  "url": "https://api.github.com/repos/ZoriHQ/zori",
  "forks_url": "https://api.github.com/repos/ZoriHQ/zori/forks",
  "keys_url": "https://api.github.com/repos/ZoriHQ/zori/keys{/key_id}",
  "collaborators_url": "https://api.github.com/repos/ZoriHQ/zori/collaborators{/collaborator}",
  "teams_url": "https://api.github.com/repos/ZoriHQ/zori/teams",
  "hooks_url": "https://api.github.com/repos/ZoriHQ/zori/hooks",
  "issue_events_url": "https://api.github.com/repos/ZoriHQ/zori/issues/events{/number}",
  "events_url": "https://api.github.com/repos/ZoriHQ/zori/events",
  "assignees_url": "https://api.github.com/repos/ZoriHQ/zori/assignees{/user}",
  "branches_url": "https://api.github.com/repos/ZoriHQ/zori/branches{/branch}",
  "tags_url": "https://api.github.com/repos/ZoriHQ/zori/tags",
  "blobs_url": "https://api.github.com/repos/ZoriHQ/zori/git/blobs{/sha}",
  "git_tags_url": "https://api.github.com/repos/ZoriHQ/zori/git/tags{/sha}",
  "git_refs_url": "https://api.github.com/repos/ZoriHQ/zori/git/refs{/sha}",
  "trees_url": "https://api.github.com/repos/ZoriHQ/zori/git/trees{/sha}",
  "statuses_url": "https://api.github.com/repos/ZoriHQ/zori/statuses/{sha}",
  "languages_url": "https://api.github.com/repos/ZoriHQ/zori/languages",
  "stargazers_url": "https://api.github.com/repos/ZoriHQ/zori/stargazers",
  "contributors_url": "https://api.github.com/repos/ZoriHQ/zori/contributors",
  "subscribers_url": "https://api.github.com/repos/ZoriHQ/zori/subscribers",
  "subscription_url": "https://api.github.com/repos/ZoriHQ/zori/subscription",
  "commits_url": "https://api.github.com/repos/ZoriHQ/zori/commits{/sha}",
  "git_commits_url": "https://api.github.com/repos/ZoriHQ/zori/git/commits{/sha}",
  "comments_url": "https://api.github.com/repos/ZoriHQ/zori/comments{/number}",
  "issue_comment_url": "https://api.github.com/repos/ZoriHQ/zori/issues/comments{/number}",
  "contents_url": "https://api.github.com/repos/ZoriHQ/zori/contents/{+path}",
  "compare_url": "https://api.github.com/repos/ZoriHQ/zori/compare/{base}...{head}",
  "merges_url": "https://api.github.com/repos/ZoriHQ/zori/merges",
  "archive_url": "https://api.github.com/repos/ZoriHQ/zori/{archive_format}{/ref}",
  "downloads_url": "https://api.github.com/repos/ZoriHQ/zori/downloads",
  "issues_url": "https://api.github.com/repos/ZoriHQ/zori/issues{/number}",
  "pulls_url": "https://api.github.com/repos/ZoriHQ/zori/pulls{/number}",
  "milestones_url": "https://api.github.com/repos/ZoriHQ/zori/milestones{/number}",
  "notifications_url": "https://api.github.com/repos/ZoriHQ/zori/notifications{?since,all,participating}",
  "labels_url": "https://api.github.com/repos/ZoriHQ/zori/labels{/name}",
  "releases_url": "https://api.github.com/repos/ZoriHQ/zori/releases{/id}",
  "deployments_url": "https://api.github.com/repos/ZoriHQ/zori/deployments",
  "created_at": "2025-10-02T19:03:36Z",
  "updated_at": "2025-12-29T00:09:38Z",
  "pushed_at": "2025-12-08T20:17:46Z",
  "git_url": "git://github.com/ZoriHQ/zori.git",
  "ssh_url": "git@github.com:ZoriHQ/zori.git",
  "clone_url": "https://github.com/ZoriHQ/zori.git",
  "svn_url": "https://github.com/ZoriHQ/zori",
  "homepage": "https://zorihq.com?utm_source=github.com",
  "size": 30871,
  "stargazers_count": 11,
  "watchers_count": 11,
  "language": "Go",
  "has_issues": true,
  "has_projects": true,
  "has_downloads": true,
  "has_wiki": true,
  "has_pages": false,
  "has_discussions": false,
  "forks_count": 0,
  "mirror_url": null,
  "archived": false,
  "disabled": false,
  "open_issues_count": 4,
  "license": {
    "key": "mit",
    "name": "MIT License",
    "spdx_id": "MIT",
    "url": "https://api.github.com/licenses/mit",
    "node_id": "MDc6TGljZW5zZTEz"
  },
  "allow_forking": true,
  "is_template": false,
  "web_commit_signoff_required": false,
  "topics": [
    "analytics",
    "productanalytics",
    "revenue",
    "revenue-tracking",
    "webanalytics"
  ],
  "visibility": "public",
  "forks": 0,
  "open_issues": 4,
  "watchers": 11,
  "default_branch": "main",
  "permissions": {
    "admin": false,
    "maintain": false,
    "push": false,
    "triage": false,
    "pull": true
  },
  "temp_clone_token": "",
  "custom_properties": {},
  "organization": {
    "login": "ZoriHQ",
    "id": 235764145,
    "node_id": "O_kgDODg15sQ",
    "avatar_url": "https://avatars.githubusercontent.com/u/235764145?v=4",
    "gravatar_id": "",
    "url": "https://api.github.com/users/ZoriHQ",
    "html_url": "https://github.com/ZoriHQ",
    "followers_url": "https://api.github.com/users/ZoriHQ/followers",
    "following_url": "https://api.github.com/users/ZoriHQ/following{/other_user}",
    "gists_url": "https://api.github.com/users/ZoriHQ/gists{/gist_id}",
    "starred_url": "https://api.github.com/users/ZoriHQ/starred{/owner}{/repo}",
    "subscriptions_url": "https://api.github.com/users/ZoriHQ/subscriptions",
    "organizations_url": "https://api.github.com/users/ZoriHQ/orgs",
    "repos_url": "https://api.github.com/users/ZoriHQ/repos",
    "events_url": "https://api.github.com/users/ZoriHQ/events{/privacy}",
    "received_events_url": "https://api.github.com/users/ZoriHQ/received_events",
    "type": "Organization",
    "user_view_type": "public",
    "site_admin": false
  },
  "network_count": 0,
  "subscribers_count": 0
}